myst_v1alpha1/__init__.py
myst_v1alpha1/client.py
myst_v1alpha1/client_test.py
myst_v1alpha1/constants.py
myst_v1alpha1/constants_test.py
myst_v1alpha1/exceptions.py
myst_v1alpha1/exceptions_test.py
myst_v1alpha1/google_id_token_auth.py
myst_v1alpha1/google_id_token_auth_test.py
myst_v1alpha1/resource.py
myst_v1alpha1/resource_test.py
myst_v1alpha1/user_credentials_cache.py
myst_v1alpha1/user_credentials_cache_test.py
myst_v1alpha1/data/__init__.py
myst_v1alpha1/data/google_oauth_client_not_so_secret.json
myst_v1alpha1/data/__pycache__/__init__.cpython-38.pyc
myst_v1alpha1/resources/__init__.py
myst_v1alpha1/resources/time_series.py
myst_v1alpha1/resources/time_series_test.py
myst_v1alpha1/utils/__init__.py
myst_v1alpha1/utils/auth_utils.py
myst_v1alpha1/utils/auth_utils_test.py
myst_v1alpha1/utils/cache_utils.py
myst_v1alpha1/utils/cache_utils_test.py
myst_v1alpha1/utils/core_utils.py
myst_v1alpha1/utils/core_utils_test.py
myst_v1alpha1/utils/requests_utils.py
myst_v1alpha1/utils/requests_utils_test.py
myst_v1alpha1/utils/retry_utils.py
myst_v1alpha1/utils/retry_utils_test.py
myst_v1alpha1/utils/validation_utils.py
myst_v1alpha1/utils/validation_utils_test.py
myst_v1alpha1-1.0.5.dist-info/LICENSE
myst_v1alpha1-1.0.5.dist-info/METADATA
myst_v1alpha1-1.0.5.dist-info/WHEEL
myst_v1alpha1-1.0.5.dist-info/top_level.txt
myst_v1alpha1-1.0.5.dist-info/RECORD
